guolei_py3_requests/__init__.py
guolei_py3_requests/library/__init__.py
guolei_py3_requests-2.0.1.dist-info/LICENSE
guolei_py3_requests-2.0.1.dist-info/METADATA
guolei_py3_requests-2.0.1.dist-info/WHEEL
guolei_py3_requests-2.0.1.dist-info/top_level.txt
guolei_py3_requests-2.0.1.dist-info/RECORD
